<Boletin_Consolidado><Boletin>
  <Numero V="0008"/>
  <Boletin_Departamental V="0012"/>
  <Tipo_Boletin V="DEPARTAMENTAL"/>
  <Desc_Corporacion V="CONSULTA POPULAR"/>
  <Departamento V="27"/>
  <Desc_Departamento V="SANTANDER"/>
  <Municipio V="031"/>
  <Desc_Municipio V="CALIFORNIA"/>
  <Dia V="21"/>
  <Mes V="8"/>
  <Anio V="2018"/>
  <Hora V="14"/>
  <Minuto V="15"/>
  <Mesas_Instaladas V="5"/>
  <Mesas_Informadas V="5"/>
  <Porc_Mesas_Informadas V="100,00"/>
  <Potencial_Sufragantes V="1689"/>
  <Detalle_Circunscripcion>
    <lin>
      <Circunscripcion V="0"/>
      <Desc_Circunscripcion V="NACIONAL"/>
      <Detalle_Pregunta>
        <lin>
          <Pregunta V="001"/>
          <Total_Sufragantes V="1689"/>
          <Porc_Sufragantes V="100,00"/>
          <Abstencion V="0"/>
          <Porc_Abstencion V="000,00"/>
          <Votos_Validos V="973"/>
          <Porc_Votos_Validos V="057,60"/>
          <Votos_No_Marcados V="364"/>
          <Porc_Votos_No_Marcados V="021,55"/>
          <Votos_Nulos V="352"/>
          <Porc_Votos_Nulos V="020,84"/>
        </lin>
        <lin>
          <Pregunta V="002"/>
          <Total_Sufragantes V="1689"/>
          <Porc_Sufragantes V="100,00"/>
          <Abstencion V="0"/>
          <Porc_Abstencion V="000,00"/>
          <Votos_Validos V="815"/>
          <Porc_Votos_Validos V="048,25"/>
          <Votos_No_Marcados V="512"/>
          <Porc_Votos_No_Marcados V="030,31"/>
          <Votos_Nulos V="362"/>
          <Porc_Votos_Nulos V="021,43"/>
        </lin>
        <lin>
          <Pregunta V="003"/>
          <Total_Sufragantes V="1689"/>
          <Porc_Sufragantes V="100,00"/>
          <Abstencion V="0"/>
          <Porc_Abstencion V="000,00"/>
          <Votos_Validos V="618"/>
          <Porc_Votos_Validos V="036,58"/>
          <Votos_No_Marcados V="524"/>
          <Porc_Votos_No_Marcados V="031,02"/>
          <Votos_Nulos V="547"/>
          <Porc_Votos_Nulos V="032,38"/>
        </lin>
        <lin>
          <Pregunta V="004"/>
          <Total_Sufragantes V="1689"/>
          <Porc_Sufragantes V="100,00"/>
          <Abstencion V="0"/>
          <Porc_Abstencion V="000,00"/>
          <Votos_Validos V="792"/>
          <Porc_Votos_Validos V="046,89"/>
          <Votos_No_Marcados V="506"/>
          <Porc_Votos_No_Marcados V="029,95"/>
          <Votos_Nulos V="391"/>
          <Porc_Votos_Nulos V="023,14"/>
        </lin>
        <lin>
          <Pregunta V="005"/>
          <Total_Sufragantes V="1689"/>
          <Porc_Sufragantes V="100,00"/>
          <Abstencion V="0"/>
          <Porc_Abstencion V="000,00"/>
          <Votos_Validos V="775"/>
          <Porc_Votos_Validos V="045,88"/>
          <Votos_No_Marcados V="449"/>
          <Porc_Votos_No_Marcados V="026,58"/>
          <Votos_Nulos V="465"/>
          <Porc_Votos_Nulos V="027,53"/>
        </lin>
        <lin>
          <Pregunta V="006"/>
          <Total_Sufragantes V="1689"/>
          <Porc_Sufragantes V="100,00"/>
          <Abstencion V="0"/>
          <Porc_Abstencion V="000,00"/>
          <Votos_Validos V="842"/>
          <Porc_Votos_Validos V="049,85"/>
          <Votos_No_Marcados V="416"/>
          <Porc_Votos_No_Marcados V="024,62"/>
          <Votos_Nulos V="431"/>
          <Porc_Votos_Nulos V="025,51"/>
        </lin>
        <lin>
          <Pregunta V="007"/>
          <Total_Sufragantes V="1689"/>
          <Porc_Sufragantes V="100,00"/>
          <Abstencion V="0"/>
          <Porc_Abstencion V="000,00"/>
          <Votos_Validos V="891"/>
          <Porc_Votos_Validos V="052,75"/>
          <Votos_No_Marcados V="416"/>
          <Porc_Votos_No_Marcados V="024,62"/>
          <Votos_Nulos V="382"/>
          <Porc_Votos_Nulos V="022,61"/>
        </lin>
      </Detalle_Pregunta>
      <Detalle_Opcion>
        <lin>
          <Opcion V="001"/>
          <Votos V="671"/>
          <Porc V="068,96"/>
          <Pregunta V="001"/>
        </lin>
        <lin>
          <Opcion V="002"/>
          <Votos V="302"/>
          <Porc V="031,03"/>
          <Pregunta V="001"/>
        </lin>
        <lin>
          <Opcion V="001"/>
          <Votos V="336"/>
          <Porc V="041,22"/>
          <Pregunta V="002"/>
        </lin>
        <lin>
          <Opcion V="002"/>
          <Votos V="479"/>
          <Porc V="058,77"/>
          <Pregunta V="002"/>
        </lin>
        <lin>
          <Opcion V="001"/>
          <Votos V="215"/>
          <Porc V="034,78"/>
          <Pregunta V="003"/>
        </lin>
        <lin>
          <Opcion V="002"/>
          <Votos V="403"/>
          <Porc V="065,21"/>
          <Pregunta V="003"/>
        </lin>
        <lin>
          <Opcion V="001"/>
          <Votos V="278"/>
          <Porc V="035,10"/>
          <Pregunta V="004"/>
        </lin>
        <lin>
          <Opcion V="002"/>
          <Votos V="514"/>
          <Porc V="064,89"/>
          <Pregunta V="004"/>
        </lin>
        <lin>
          <Opcion V="001"/>
          <Votos V="360"/>
          <Porc V="046,45"/>
          <Pregunta V="005"/>
        </lin>
        <lin>
          <Opcion V="002"/>
          <Votos V="415"/>
          <Porc V="053,54"/>
          <Pregunta V="005"/>
        </lin>
        <lin>
          <Opcion V="001"/>
          <Votos V="435"/>
          <Porc V="051,66"/>
          <Pregunta V="006"/>
        </lin>
        <lin>
          <Opcion V="002"/>
          <Votos V="407"/>
          <Porc V="048,33"/>
          <Pregunta V="006"/>
        </lin>
        <lin>
          <Opcion V="001"/>
          <Votos V="514"/>
          <Porc V="057,68"/>
          <Pregunta V="007"/>
        </lin>
        <lin>
          <Opcion V="002"/>
          <Votos V="377"/>
          <Porc V="042,31"/>
          <Pregunta V="007"/>
        </lin>
      </Detalle_Opcion>
    </lin>
  </Detalle_Circunscripcion>
</Boletin>
</Boletin_Consolidado>