<Boletin_Consolidado><Boletin>
  <Numero V="0008"/>
  <Boletin_Departamental V="0012"/>
  <Tipo_Boletin V="DEPARTAMENTAL"/>
  <Desc_Corporacion V="CONSULTA POPULAR"/>
  <Departamento V="23"/>
  <Desc_Departamento V="NARIÑO"/>
  <Municipio V="085"/>
  <Desc_Municipio V="LOS ANDES (SOTOMAYOR)"/>
  <Dia V="21"/>
  <Mes V="8"/>
  <Anio V="2018"/>
  <Hora V="14"/>
  <Minuto V="15"/>
  <Mesas_Instaladas V="23"/>
  <Mesas_Informadas V="23"/>
  <Porc_Mesas_Informadas V="100,00"/>
  <Potencial_Sufragantes V="7338"/>
  <Detalle_Circunscripcion>
    <lin>
      <Circunscripcion V="0"/>
      <Desc_Circunscripcion V="NACIONAL"/>
      <Detalle_Pregunta>
        <lin>
          <Pregunta V="001"/>
          <Total_Sufragantes V="7338"/>
          <Porc_Sufragantes V="100,00"/>
          <Abstencion V="0"/>
          <Porc_Abstencion V="000,00"/>
          <Votos_Validos V="3533"/>
          <Porc_Votos_Validos V="048,14"/>
          <Votos_No_Marcados V="2423"/>
          <Porc_Votos_No_Marcados V="033,01"/>
          <Votos_Nulos V="1382"/>
          <Porc_Votos_Nulos V="018,83"/>
        </lin>
        <lin>
          <Pregunta V="002"/>
          <Total_Sufragantes V="7338"/>
          <Porc_Sufragantes V="100,00"/>
          <Abstencion V="0"/>
          <Porc_Abstencion V="000,00"/>
          <Votos_Validos V="4067"/>
          <Porc_Votos_Validos V="055,42"/>
          <Votos_No_Marcados V="1610"/>
          <Porc_Votos_No_Marcados V="021,94"/>
          <Votos_Nulos V="1661"/>
          <Porc_Votos_Nulos V="022,63"/>
        </lin>
        <lin>
          <Pregunta V="003"/>
          <Total_Sufragantes V="7338"/>
          <Porc_Sufragantes V="100,00"/>
          <Abstencion V="0"/>
          <Porc_Abstencion V="000,00"/>
          <Votos_Validos V="3925"/>
          <Porc_Votos_Validos V="053,48"/>
          <Votos_No_Marcados V="1164"/>
          <Porc_Votos_No_Marcados V="015,86"/>
          <Votos_Nulos V="2249"/>
          <Porc_Votos_Nulos V="030,64"/>
        </lin>
        <lin>
          <Pregunta V="004"/>
          <Total_Sufragantes V="7338"/>
          <Porc_Sufragantes V="100,00"/>
          <Abstencion V="0"/>
          <Porc_Abstencion V="000,00"/>
          <Votos_Validos V="3586"/>
          <Porc_Votos_Validos V="048,86"/>
          <Votos_No_Marcados V="1751"/>
          <Porc_Votos_No_Marcados V="023,86"/>
          <Votos_Nulos V="2001"/>
          <Porc_Votos_Nulos V="027,26"/>
        </lin>
        <lin>
          <Pregunta V="005"/>
          <Total_Sufragantes V="7338"/>
          <Porc_Sufragantes V="100,00"/>
          <Abstencion V="0"/>
          <Porc_Abstencion V="000,00"/>
          <Votos_Validos V="4127"/>
          <Porc_Votos_Validos V="056,24"/>
          <Votos_No_Marcados V="1649"/>
          <Porc_Votos_No_Marcados V="022,47"/>
          <Votos_Nulos V="1562"/>
          <Porc_Votos_Nulos V="021,28"/>
        </lin>
        <lin>
          <Pregunta V="006"/>
          <Total_Sufragantes V="7338"/>
          <Porc_Sufragantes V="100,00"/>
          <Abstencion V="0"/>
          <Porc_Abstencion V="000,00"/>
          <Votos_Validos V="4335"/>
          <Porc_Votos_Validos V="059,07"/>
          <Votos_No_Marcados V="1271"/>
          <Porc_Votos_No_Marcados V="017,32"/>
          <Votos_Nulos V="1732"/>
          <Porc_Votos_Nulos V="023,60"/>
        </lin>
        <lin>
          <Pregunta V="007"/>
          <Total_Sufragantes V="7338"/>
          <Porc_Sufragantes V="100,00"/>
          <Abstencion V="0"/>
          <Porc_Abstencion V="000,00"/>
          <Votos_Validos V="3630"/>
          <Porc_Votos_Validos V="049,46"/>
          <Votos_No_Marcados V="1943"/>
          <Porc_Votos_No_Marcados V="026,47"/>
          <Votos_Nulos V="1765"/>
          <Porc_Votos_Nulos V="024,05"/>
        </lin>
      </Detalle_Pregunta>
      <Detalle_Opcion>
        <lin>
          <Opcion V="001"/>
          <Votos V="1673"/>
          <Porc V="047,35"/>
          <Pregunta V="001"/>
        </lin>
        <lin>
          <Opcion V="002"/>
          <Votos V="1860"/>
          <Porc V="052,64"/>
          <Pregunta V="001"/>
        </lin>
        <lin>
          <Opcion V="001"/>
          <Votos V="2002"/>
          <Porc V="049,22"/>
          <Pregunta V="002"/>
        </lin>
        <lin>
          <Opcion V="002"/>
          <Votos V="2065"/>
          <Porc V="050,77"/>
          <Pregunta V="002"/>
        </lin>
        <lin>
          <Opcion V="001"/>
          <Votos V="2074"/>
          <Porc V="052,84"/>
          <Pregunta V="003"/>
        </lin>
        <lin>
          <Opcion V="002"/>
          <Votos V="1851"/>
          <Porc V="047,15"/>
          <Pregunta V="003"/>
        </lin>
        <lin>
          <Opcion V="001"/>
          <Votos V="1738"/>
          <Porc V="048,46"/>
          <Pregunta V="004"/>
        </lin>
        <lin>
          <Opcion V="002"/>
          <Votos V="1848"/>
          <Porc V="051,53"/>
          <Pregunta V="004"/>
        </lin>
        <lin>
          <Opcion V="001"/>
          <Votos V="2025"/>
          <Porc V="049,06"/>
          <Pregunta V="005"/>
        </lin>
        <lin>
          <Opcion V="002"/>
          <Votos V="2102"/>
          <Porc V="050,93"/>
          <Pregunta V="005"/>
        </lin>
        <lin>
          <Opcion V="001"/>
          <Votos V="2137"/>
          <Porc V="049,29"/>
          <Pregunta V="006"/>
        </lin>
        <lin>
          <Opcion V="002"/>
          <Votos V="2198"/>
          <Porc V="050,70"/>
          <Pregunta V="006"/>
        </lin>
        <lin>
          <Opcion V="001"/>
          <Votos V="1408"/>
          <Porc V="038,78"/>
          <Pregunta V="007"/>
        </lin>
        <lin>
          <Opcion V="002"/>
          <Votos V="2222"/>
          <Porc V="061,21"/>
          <Pregunta V="007"/>
        </lin>
      </Detalle_Opcion>
    </lin>
  </Detalle_Circunscripcion>
</Boletin>
</Boletin_Consolidado>