<Boletin_Consolidado><Boletin>
  <Numero V="0008"/>
  <Boletin_Departamental V="0012"/>
  <Tipo_Boletin V="DEPARTAMENTAL"/>
  <Desc_Corporacion V="CONSULTA POPULAR"/>
  <Departamento V="88"/>
  <Desc_Departamento V="CONSULADOS"/>
  <Municipio V="690"/>
  <Desc_Municipio V="REPUBLICA SOCIALISTA DEVIETNAM"/>
  <Dia V="21"/>
  <Mes V="8"/>
  <Anio V="2018"/>
  <Hora V="14"/>
  <Minuto V="15"/>
  <Mesas_Instaladas V="7"/>
  <Mesas_Informadas V="7"/>
  <Porc_Mesas_Informadas V="100,00"/>
  <Potencial_Sufragantes V="41"/>
  <Detalle_Circunscripcion>
    <lin>
      <Circunscripcion V="0"/>
      <Desc_Circunscripcion V="NACIONAL"/>
      <Detalle_Pregunta>
        <lin>
          <Pregunta V="001"/>
          <Total_Sufragantes V="41"/>
          <Porc_Sufragantes V="100,00"/>
          <Abstencion V="0"/>
          <Porc_Abstencion V="000,00"/>
          <Votos_Validos V="5"/>
          <Porc_Votos_Validos V="012,19"/>
          <Votos_No_Marcados V="21"/>
          <Porc_Votos_No_Marcados V="051,21"/>
          <Votos_Nulos V="15"/>
          <Porc_Votos_Nulos V="036,58"/>
        </lin>
        <lin>
          <Pregunta V="002"/>
          <Total_Sufragantes V="41"/>
          <Porc_Sufragantes V="100,00"/>
          <Abstencion V="0"/>
          <Porc_Abstencion V="000,00"/>
          <Votos_Validos V="28"/>
          <Porc_Votos_Validos V="068,29"/>
          <Votos_No_Marcados V="4"/>
          <Porc_Votos_No_Marcados V="009,75"/>
          <Votos_Nulos V="9"/>
          <Porc_Votos_Nulos V="021,95"/>
        </lin>
        <lin>
          <Pregunta V="003"/>
          <Total_Sufragantes V="41"/>
          <Porc_Sufragantes V="100,00"/>
          <Abstencion V="0"/>
          <Porc_Abstencion V="000,00"/>
          <Votos_Validos V="15"/>
          <Porc_Votos_Validos V="036,58"/>
          <Votos_No_Marcados V="12"/>
          <Porc_Votos_No_Marcados V="029,26"/>
          <Votos_Nulos V="14"/>
          <Porc_Votos_Nulos V="034,14"/>
        </lin>
        <lin>
          <Pregunta V="004"/>
          <Total_Sufragantes V="41"/>
          <Porc_Sufragantes V="100,00"/>
          <Abstencion V="0"/>
          <Porc_Abstencion V="000,00"/>
          <Votos_Validos V="6"/>
          <Porc_Votos_Validos V="014,63"/>
          <Votos_No_Marcados V="15"/>
          <Porc_Votos_No_Marcados V="036,58"/>
          <Votos_Nulos V="20"/>
          <Porc_Votos_Nulos V="048,78"/>
        </lin>
        <lin>
          <Pregunta V="005"/>
          <Total_Sufragantes V="41"/>
          <Porc_Sufragantes V="100,00"/>
          <Abstencion V="0"/>
          <Porc_Abstencion V="000,00"/>
          <Votos_Validos V="19"/>
          <Porc_Votos_Validos V="046,34"/>
          <Votos_No_Marcados V="20"/>
          <Porc_Votos_No_Marcados V="048,78"/>
          <Votos_Nulos V="2"/>
          <Porc_Votos_Nulos V="004,87"/>
        </lin>
        <lin>
          <Pregunta V="006"/>
          <Total_Sufragantes V="41"/>
          <Porc_Sufragantes V="100,00"/>
          <Abstencion V="0"/>
          <Porc_Abstencion V="000,00"/>
          <Votos_Validos V="13"/>
          <Porc_Votos_Validos V="031,70"/>
          <Votos_No_Marcados V="24"/>
          <Porc_Votos_No_Marcados V="058,53"/>
          <Votos_Nulos V="4"/>
          <Porc_Votos_Nulos V="009,75"/>
        </lin>
        <lin>
          <Pregunta V="007"/>
          <Total_Sufragantes V="41"/>
          <Porc_Sufragantes V="100,00"/>
          <Abstencion V="0"/>
          <Porc_Abstencion V="000,00"/>
          <Votos_Validos V="15"/>
          <Porc_Votos_Validos V="036,58"/>
          <Votos_No_Marcados V="5"/>
          <Porc_Votos_No_Marcados V="012,19"/>
          <Votos_Nulos V="21"/>
          <Porc_Votos_Nulos V="051,21"/>
        </lin>
      </Detalle_Pregunta>
      <Detalle_Opcion>
        <lin>
          <Opcion V="001"/>
          <Votos V="4"/>
          <Porc V="080,00"/>
          <Pregunta V="001"/>
        </lin>
        <lin>
          <Opcion V="002"/>
          <Votos V="1"/>
          <Porc V="020,00"/>
          <Pregunta V="001"/>
        </lin>
        <lin>
          <Opcion V="001"/>
          <Votos V="4"/>
          <Porc V="014,28"/>
          <Pregunta V="002"/>
        </lin>
        <lin>
          <Opcion V="002"/>
          <Votos V="24"/>
          <Porc V="085,71"/>
          <Pregunta V="002"/>
        </lin>
        <lin>
          <Opcion V="001"/>
          <Votos V="6"/>
          <Porc V="040,00"/>
          <Pregunta V="003"/>
        </lin>
        <lin>
          <Opcion V="002"/>
          <Votos V="9"/>
          <Porc V="060,00"/>
          <Pregunta V="003"/>
        </lin>
        <lin>
          <Opcion V="001"/>
          <Votos V="1"/>
          <Porc V="016,66"/>
          <Pregunta V="004"/>
        </lin>
        <lin>
          <Opcion V="002"/>
          <Votos V="5"/>
          <Porc V="083,33"/>
          <Pregunta V="004"/>
        </lin>
        <lin>
          <Opcion V="001"/>
          <Votos V="17"/>
          <Porc V="089,47"/>
          <Pregunta V="005"/>
        </lin>
        <lin>
          <Opcion V="002"/>
          <Votos V="2"/>
          <Porc V="010,52"/>
          <Pregunta V="005"/>
        </lin>
        <lin>
          <Opcion V="001"/>
          <Votos V="11"/>
          <Porc V="084,61"/>
          <Pregunta V="006"/>
        </lin>
        <lin>
          <Opcion V="002"/>
          <Votos V="2"/>
          <Porc V="015,38"/>
          <Pregunta V="006"/>
        </lin>
        <lin>
          <Opcion V="001"/>
          <Votos V="13"/>
          <Porc V="086,66"/>
          <Pregunta V="007"/>
        </lin>
        <lin>
          <Opcion V="002"/>
          <Votos V="2"/>
          <Porc V="013,33"/>
          <Pregunta V="007"/>
        </lin>
      </Detalle_Opcion>
    </lin>
  </Detalle_Circunscripcion>
</Boletin>
</Boletin_Consolidado>