<Boletin_Consolidado><Boletin>
  <Numero V="0008"/>
  <Boletin_Departamental V="0012"/>
  <Tipo_Boletin V="DEPARTAMENTAL"/>
  <Desc_Corporacion V="CONSULTA POPULAR"/>
  <Departamento V="48"/>
  <Desc_Departamento V="LA GUAJIRA"/>
  <Municipio V="011"/>
  <Desc_Municipio V="MANAURE"/>
  <Dia V="21"/>
  <Mes V="8"/>
  <Anio V="2018"/>
  <Hora V="14"/>
  <Minuto V="15"/>
  <Mesas_Instaladas V="148"/>
  <Mesas_Informadas V="148"/>
  <Porc_Mesas_Informadas V="100,00"/>
  <Potencial_Sufragantes V="54831"/>
  <Detalle_Circunscripcion>
    <lin>
      <Circunscripcion V="0"/>
      <Desc_Circunscripcion V="NACIONAL"/>
      <Detalle_Pregunta>
        <lin>
          <Pregunta V="001"/>
          <Total_Sufragantes V="54831"/>
          <Porc_Sufragantes V="100,00"/>
          <Abstencion V="0"/>
          <Porc_Abstencion V="000,00"/>
          <Votos_Validos V="26543"/>
          <Porc_Votos_Validos V="048,40"/>
          <Votos_No_Marcados V="14158"/>
          <Porc_Votos_No_Marcados V="025,82"/>
          <Votos_Nulos V="14130"/>
          <Porc_Votos_Nulos V="025,77"/>
        </lin>
        <lin>
          <Pregunta V="002"/>
          <Total_Sufragantes V="54831"/>
          <Porc_Sufragantes V="100,00"/>
          <Abstencion V="0"/>
          <Porc_Abstencion V="000,00"/>
          <Votos_Validos V="26357"/>
          <Porc_Votos_Validos V="048,06"/>
          <Votos_No_Marcados V="12347"/>
          <Porc_Votos_No_Marcados V="022,51"/>
          <Votos_Nulos V="16127"/>
          <Porc_Votos_Nulos V="029,41"/>
        </lin>
        <lin>
          <Pregunta V="003"/>
          <Total_Sufragantes V="54831"/>
          <Porc_Sufragantes V="100,00"/>
          <Abstencion V="0"/>
          <Porc_Abstencion V="000,00"/>
          <Votos_Validos V="27089"/>
          <Porc_Votos_Validos V="049,40"/>
          <Votos_No_Marcados V="13929"/>
          <Porc_Votos_No_Marcados V="025,40"/>
          <Votos_Nulos V="13813"/>
          <Porc_Votos_Nulos V="025,19"/>
        </lin>
        <lin>
          <Pregunta V="004"/>
          <Total_Sufragantes V="54831"/>
          <Porc_Sufragantes V="100,00"/>
          <Abstencion V="0"/>
          <Porc_Abstencion V="000,00"/>
          <Votos_Validos V="27803"/>
          <Porc_Votos_Validos V="050,70"/>
          <Votos_No_Marcados V="14083"/>
          <Porc_Votos_No_Marcados V="025,68"/>
          <Votos_Nulos V="12945"/>
          <Porc_Votos_Nulos V="023,60"/>
        </lin>
        <lin>
          <Pregunta V="005"/>
          <Total_Sufragantes V="54831"/>
          <Porc_Sufragantes V="100,00"/>
          <Abstencion V="0"/>
          <Porc_Abstencion V="000,00"/>
          <Votos_Validos V="28315"/>
          <Porc_Votos_Validos V="051,64"/>
          <Votos_No_Marcados V="12711"/>
          <Porc_Votos_No_Marcados V="023,18"/>
          <Votos_Nulos V="13805"/>
          <Porc_Votos_Nulos V="025,17"/>
        </lin>
        <lin>
          <Pregunta V="006"/>
          <Total_Sufragantes V="54831"/>
          <Porc_Sufragantes V="100,00"/>
          <Abstencion V="0"/>
          <Porc_Abstencion V="000,00"/>
          <Votos_Validos V="27569"/>
          <Porc_Votos_Validos V="050,27"/>
          <Votos_No_Marcados V="12973"/>
          <Porc_Votos_No_Marcados V="023,65"/>
          <Votos_Nulos V="14289"/>
          <Porc_Votos_Nulos V="026,06"/>
        </lin>
        <lin>
          <Pregunta V="007"/>
          <Total_Sufragantes V="54831"/>
          <Porc_Sufragantes V="100,00"/>
          <Abstencion V="0"/>
          <Porc_Abstencion V="000,00"/>
          <Votos_Validos V="26294"/>
          <Porc_Votos_Validos V="047,95"/>
          <Votos_No_Marcados V="13961"/>
          <Porc_Votos_No_Marcados V="025,46"/>
          <Votos_Nulos V="14576"/>
          <Porc_Votos_Nulos V="026,58"/>
        </lin>
      </Detalle_Pregunta>
      <Detalle_Opcion>
        <lin>
          <Opcion V="001"/>
          <Votos V="13870"/>
          <Porc V="052,25"/>
          <Pregunta V="001"/>
        </lin>
        <lin>
          <Opcion V="002"/>
          <Votos V="12673"/>
          <Porc V="047,74"/>
          <Pregunta V="001"/>
        </lin>
        <lin>
          <Opcion V="001"/>
          <Votos V="14311"/>
          <Porc V="054,29"/>
          <Pregunta V="002"/>
        </lin>
        <lin>
          <Opcion V="002"/>
          <Votos V="12046"/>
          <Porc V="045,70"/>
          <Pregunta V="002"/>
        </lin>
        <lin>
          <Opcion V="001"/>
          <Votos V="13391"/>
          <Porc V="049,43"/>
          <Pregunta V="003"/>
        </lin>
        <lin>
          <Opcion V="002"/>
          <Votos V="13698"/>
          <Porc V="050,56"/>
          <Pregunta V="003"/>
        </lin>
        <lin>
          <Opcion V="001"/>
          <Votos V="14054"/>
          <Porc V="050,54"/>
          <Pregunta V="004"/>
        </lin>
        <lin>
          <Opcion V="002"/>
          <Votos V="13749"/>
          <Porc V="049,45"/>
          <Pregunta V="004"/>
        </lin>
        <lin>
          <Opcion V="001"/>
          <Votos V="13679"/>
          <Porc V="048,31"/>
          <Pregunta V="005"/>
        </lin>
        <lin>
          <Opcion V="002"/>
          <Votos V="14636"/>
          <Porc V="051,68"/>
          <Pregunta V="005"/>
        </lin>
        <lin>
          <Opcion V="001"/>
          <Votos V="13738"/>
          <Porc V="049,83"/>
          <Pregunta V="006"/>
        </lin>
        <lin>
          <Opcion V="002"/>
          <Votos V="13831"/>
          <Porc V="050,16"/>
          <Pregunta V="006"/>
        </lin>
        <lin>
          <Opcion V="001"/>
          <Votos V="13637"/>
          <Porc V="051,86"/>
          <Pregunta V="007"/>
        </lin>
        <lin>
          <Opcion V="002"/>
          <Votos V="12657"/>
          <Porc V="048,13"/>
          <Pregunta V="007"/>
        </lin>
      </Detalle_Opcion>
    </lin>
  </Detalle_Circunscripcion>
</Boletin>
</Boletin_Consolidado>